PandaAuthPy/__init__.py
PandaAuthPy/auth.py
pandaauthpy-1.0.2.dist-info/METADATA
pandaauthpy-1.0.2.dist-info/WHEEL
pandaauthpy-1.0.2.dist-info/top_level.txt
pandaauthpy-1.0.2.dist-info/RECORD
