Metadata-Version: 2.2
Name: PandaAuthPy
Version: 1.0.2
Summary: A Panda-Auth library for Python.
Home-page: https://github.com/yourusername/PandaAuthPy
Author: Rice Jay
Author-email: yvor.exe@example.com
Classifier: Programming Language :: Python :: 3
Classifier: License :: OSI Approved :: MIT License
Classifier: Operating System :: OS Independent
Requires-Python: >=3.6
Requires-Dist: requests
Dynamic: author
Dynamic: author-email
Dynamic: classifier
Dynamic: description
Dynamic: description-content-type
Dynamic: home-page
Dynamic: requires-dist
Dynamic: requires-python
Dynamic: summary
